README.md
setup.cfg
setup.py
pyobb/__init__.py
pyobb/obb.py
pyobb.egg-info/PKG-INFO
pyobb.egg-info/SOURCES.txt
pyobb.egg-info/dependency_links.txt
pyobb.egg-info/requires.txt
pyobb.egg-info/top_level.txt