Metadata-Version: 1.1
Name: pyobb
Version: 1.0.2
Summary: Python OBB Implementation
Home-page: https://github.com/pboechat/pyobb
Author: Pedro Boechat
Author-email: pboechat@gmail.com
License: UNKNOWN
Download-URL: https://github.com/pboechat/pyobb/archive/1.0.2.tar.gz
Keywords: obb,computational-geometry,oriented-bounding-box
Platform: UNKNOWN
